pySwarmbytes/__init__.py
pySwarmbytes/exceptions.py
pySwarmbytes/sb.py
pySwarmbytes-0.1.1.dist-info/LICENSE
pySwarmbytes-0.1.1.dist-info/METADATA
pySwarmbytes-0.1.1.dist-info/WHEEL
pySwarmbytes-0.1.1.dist-info/top_level.txt
pySwarmbytes-0.1.1.dist-info/RECORD
