Metadata-Version: 2.1
Name: pySwarmbytes
Version: 0.1.1
Summary: UNOFFICIAL Python bindings for Swarmbytes Dashboard API
Home-page: https://github.com/coder-amogh/pySwarmbytes
Author: coder-amogh (Amogh Datar)
License: UNKNOWN
Project-URL: Bug Tracker, https://github.com/coder-amogh/pySwarmbytes/issues
Keywords: python,swarmbytes,hg,passive income,swarmbytes api,swarmbytes dashboard,python swarmbytes
Platform: UNKNOWN
Classifier: Development Status :: 5 - Production/Stable
Classifier: Intended Audience :: Developers
Classifier: Programming Language :: Python :: 3
Classifier: Operating System :: OS Independent
Requires-Dist: requests
Requires-Dist: pySocks
Requires-Dist: beautifulsoup4
